CHANGELOG.md
MANIFEST.in
README.md
setup.cfg
setup.py
versioneer.py
src/libreflow/__init__.py
src/libreflow.extensions.2h14.publish.egg-info/PKG-INFO
src/libreflow.extensions.2h14.publish.egg-info/SOURCES.txt
src/libreflow.extensions.2h14.publish.egg-info/dependency_links.txt
src/libreflow.extensions.2h14.publish.egg-info/top_level.txt
src/libreflow/extensions/__init__.py
src/libreflow/extensions/2h14/__init__.py
src/libreflow/extensions/2h14/publish/__init__.py
src/libreflow/extensions/2h14/publish/_version.py